dhananjayan/__init__.py
dhananjayan/about/__init__.py
dhananjayan/blog/AIzero2hero.py
dhananjayan/blog/__init__.py
dhananjayan/cv/__init__.py
dhananjayan/resume/__init__.py
dhananjayan-1.0.0.dist-info/METADATA
dhananjayan-1.0.0.dist-info/WHEEL
dhananjayan-1.0.0.dist-info/top_level.txt
dhananjayan-1.0.0.dist-info/RECORD
