Metadata-Version: 2.1
Name: dhananjayan
Version: 1.0.0
Summary: A python library to act as my blog/cv
Author: Dhananjayan Sudhakar
Author-email: vvandhiyadhevan@gmail.com
